objectio/__init__.py
objectio/checks.py
objectio/io.py
objectio-0.2.29.data/scripts/obj
objectio-0.2.29.dist-info/LICENSE
objectio-0.2.29.dist-info/METADATA
objectio-0.2.29.dist-info/WHEEL
objectio-0.2.29.dist-info/top_level.txt
objectio-0.2.29.dist-info/RECORD
