Metadata-Version: 2.1
Name: objectio
Version: 0.2.29
Summary: Generic object storage interface and commands.
Home-page: http://github.com/tmbdev/objectio
Author: Thomas Breuel
Author-email: tmbdev+removeme@gmail.com
License: MIT
Keywords: object store,client,deep learning
Platform: UNKNOWN
Classifier: Development Status :: 3 - Alpha
Classifier: License :: OSI Approved :: BSD License
Classifier: Programming Language :: Python :: 3.6
Classifier: Programming Language :: Python :: 3.7
Requires-Python: >=3.6
Requires-Dist: pyyaml
Requires-Dist: braceexpand
Requires-Dist: simplejson
Requires-Dist: typer
